<?xml version="1.0" encoding="UTF-8"?><full-text-retrieval-response xmlns="http://www.elsevier.com/xml/svapi/article/dtd" xmlns:bk="http://www.elsevier.com/xml/bk/dtd" xmlns:cals="http://www.elsevier.com/xml/common/cals/dtd" xmlns:ce="http://www.elsevier.com/xml/common/dtd" xmlns:ja="http://www.elsevier.com/xml/ja/dtd" xmlns:mml="http://www.w3.org/1998/Math/MathML" xmlns:sa="http://www.elsevier.com/xml/common/struct-aff/dtd" xmlns:sb="http://www.elsevier.com/xml/common/struct-bib/dtd" xmlns:tb="http://www.elsevier.com/xml/common/table/dtd" xmlns:xlink="http://www.w3.org/1999/xlink" xmlns:xocs="http://www.elsevier.com/xml/xocs/dtd" xmlns:dc="http://purl.org/dc/elements/1.1/" xmlns:dcterms="http://purl.org/dc/terms/" xmlns:prism="http://prismstandard.org/namespaces/basic/2.0/" xmlns:xsi="http://www.w3.org/2001/XMLSchema-instance"><coredata><prism:url>https://api.elsevier.com/content/article/pii/S0080878408625715</prism:url><dc:identifier>doi:10.1016/S0080-8784(08)62571-5</dc:identifier><eid>1-s2.0-S0080878408625715</eid><prism:doi>10.1016/S0080-8784(08)62571-5</prism:doi><pii>S0080-8784(08)62571-5</pii><dc:title>Chapter 7 Post-CMP Clean </dc:title><prism:publicationName>Semiconductors and Semimetals</prism:publicationName><prism:aggregationType>Book Series</prism:aggregationType><pubType>fla</pubType><prism:issn>00808784</prism:issn><prism:isbn>9780127521725</prism:isbn><prism:volume>63</prism:volume><prism:startingPage>183</prism:startingPage><prism:endingPage>214</prism:endingPage><prism:pageRange>183-214</prism:pageRange><dcterms:isPartOf>urn:isbn:978-0-12-752172-5</dcterms:isPartOf><dc:format>application/xml</dc:format><prism:coverDate>1999-12-31</prism:coverDate><prism:coverDisplayDate>1999</prism:coverDisplayDate><prism:copyright>Copyright © 2000 Academic Press. Published by Elsevier Ltd. All rights reserved.</prism:copyright><prism:publisher>Academic Press. Published by Elsevier Ltd.</prism:publisher><prism:issueName>Chemical Mechanical Polishing in Silicon Processing</prism:issueName><dc:creator>Tardif, François</dc:creator><dc:description>
                  The understanding of post-chemical–mechanical polishing (post-CMP) cleaning processes requires some basic knowledge of electrochemistry and colloid sciences. With the decrease of device dimensions, planarization of both front- and back-end layers by CMP is imperative for technologies smaller than 0.5 μm. CMP applications, currently, concern both front-end steps such as shallow trench isolation (STI) and intermetal dielectric (IMD) in the back end of the line. For more advanced technologies where the damascene structure is adopted, outcropping metals such as aluminum, copper, tungsten, titanium, titanium nitride, tantalum, and tantalum nitride may be present with the silicon oxide. The behavior of these metals must be checked in the actual device configurations because of the simultaneous presence of two different metals—conductor and diffusion barrier—that induce different electrochemical potentials.
               </dc:description><openaccess>0</openaccess><openaccessArticle>false</openaccessArticle><openaccessType/><openArchiveArticle>false</openArchiveArticle><openaccessSponsorName/><openaccessSponsorType/><openaccessUserLicense/><link href="https://api.elsevier.com/content/article/pii/S0080878408625715" rel="self"/><link href="https://www.sciencedirect.com/science/article/pii/S0080878408625715" rel="scidir"/></coredata><scopus-id>0343129277</scopus-id><scopus-eid>2-s2.0-0343129277</scopus-eid><link href="https://api.elsevier.com/content/abstract/scopus_id/0343129277" rel="abstract"/><originalText><xocs:doc><xocs:meta><xocs:open-access xmlns:xocs="http://www.elsevier.com/xml/xocs/dtd"
                  xmlns:xsi="http://www.w3.org/2001/XMLSchema-instance"
                  xmlns:xoe="http://www.elsevier.com/xml/xoe/dtd">
   <xocs:oa-article-status is-open-access="0" is-open-archive="0"/>
</xocs:open-access><xocs:available-online-date xmlns:xoe="http://www.elsevier.com/xml/xoe/dtd" yyyymmdd="20080530">2008-05-30</xocs:available-online-date></xocs:meta></xocs:doc></originalText></full-text-retrieval-response>